GooseBib/PNAS-USA.yaml
GooseBib/PNAS.yaml
GooseBib/__init__.py
GooseBib/_version.py
GooseBib/arXiv.yaml
GooseBib/bibtex.py
GooseBib/journals.py
GooseBib/mechanics.yaml
GooseBib/physics.yaml
GooseBib/recognise.py
GooseBib/reformat.py
GooseBib/tex.py
GooseBib/cli/GbibCheckAuthors.py
GooseBib/cli/GbibCheckKeys.py
GooseBib/cli/GbibCheckLink.py
GooseBib/cli/GbibList.py
GooseBib/cli/GbibParse.py
GooseBib/cli/GbibSelect.py
GooseBib/cli/GbibSelectAlias.py
GooseBib/cli/__init__.py
GooseBib-0.9.4.dist-info/LICENSE
GooseBib-0.9.4.dist-info/METADATA
GooseBib-0.9.4.dist-info/WHEEL
GooseBib-0.9.4.dist-info/entry_points.txt
GooseBib-0.9.4.dist-info/top_level.txt
GooseBib-0.9.4.dist-info/RECORD
