Metadata-Version: 2.1
Name: GooseBib
Version: 0.9.4
Summary: Reformat BibTeX files
Author-email: Tom de Geus <tom@geus.me>
Project-URL: Source, https://github.com/tdegeus/GooseBib
Classifier: License :: OSI Approved :: MIT License
Requires-Python: >=3.6
License-File: LICENSE
Requires-Dist: arxiv
Requires-Dist: bibtexparser
Requires-Dist: click
Requires-Dist: docopt
Requires-Dist: GitPython
Requires-Dist: numpy
Requires-Dist: PyYAML
Requires-Dist: requests
Requires-Dist: tqdm
